dmpe/__init__.py
dmpe/algorithms/__init__.py
dmpe/algorithms/algorithm_utils.py
dmpe/algorithms/algorithms.py
dmpe/evaluation/__init__.py
dmpe/evaluation/callbacks.py
dmpe/evaluation/experiment_utils.py
dmpe/evaluation/metrics_utils.py
dmpe/evaluation/plotting_utils.py
dmpe/evaluation/scripts/__init__.py
dmpe/evaluation/scripts/create_exp_directories.py
dmpe/evaluation/scripts/classical_systems/__init__.py
dmpe/evaluation/scripts/classical_systems/dmpe_eval.py
dmpe/evaluation/scripts/classical_systems/igoats_eval.py
dmpe/evaluation/scripts/classical_systems/perfect_model_dmpe_eval.py
dmpe/evaluation/scripts/classical_systems/sgoats_eval.py
dmpe/evaluation/scripts/pmsm/__init__.py
dmpe/evaluation/scripts/pmsm/dmpe_params.py
dmpe/evaluation/scripts/pmsm/eval_dmpe.py
dmpe/evaluation/scripts/pmsm/eval_goats.py
dmpe/evaluation/scripts/pmsm/eval_pi_sweep.py
dmpe/evaluation/scripts/pmsm/eval_random_walk.py
dmpe/evaluation/scripts/pmsm/goats_params.py
dmpe/evaluation/scripts/pmsm/run_multiple.py
dmpe/excitation/__init__.py
dmpe/excitation/excitation_utils.py
dmpe/models/__init__.py
dmpe/models/model_training.py
dmpe/models/model_utils.py
dmpe/models/models.py
dmpe/models/rls.py
dmpe/related_work/__init__.py
dmpe/related_work/algorithms.py
dmpe/related_work/excitation_utils.py
dmpe/related_work/mixed_GA.py
dmpe/related_work/multitasking_tsp.py
dmpe/related_work/np_reimpl/__init__.py
dmpe/related_work/np_reimpl/env_utils.py
dmpe/related_work/np_reimpl/metrics.py
dmpe/utils/__init__.py
dmpe/utils/density_estimation.py
dmpe/utils/metrics.py
dmpe/utils/signals.py
dmpe/utils/env_utils/foc_pi.py
dmpe/utils/env_utils/pmsm_utils.py
dmpe-0.2.4.dist-info/licenses/LICENSE
dmpe-0.2.4.dist-info/METADATA
dmpe-0.2.4.dist-info/WHEEL
dmpe-0.2.4.dist-info/top_level.txt
dmpe-0.2.4.dist-info/RECORD
