Metadata-Version: 2.4
Name: dmpe
Version: 0.2.4
Summary: Excitation of exciting systems through differentiable model predictive excitation
Author-email: Hendrik Vater <vater@lea.uni-paderborn.de>
Project-URL: Homepage, https://github.com/ExcitingSystems/DMPE
Project-URL: Issues, https://github.com/ExcitingSystems/DMPE/issues
Classifier: Programming Language :: Python :: 3
Classifier: License :: OSI Approved :: GNU General Public License (GPL)
Classifier: License :: OSI Approved :: GNU General Public License v3 (GPLv3)
Classifier: Operating System :: POSIX :: Linux
Requires-Python: >=3.11
License-File: LICENSE
Requires-Dist: numpy==1.26.4
Requires-Dist: scipy==1.13.1
Requires-Dist: matplotlib==3.9.0
Requires-Dist: tqdm==4.66.4
Requires-Dist: jax[cuda12]==0.4.28; sys_platform == "linux"
Requires-Dist: jax==0.4.28; sys_platform == "win32"
Requires-Dist: jaxlib==0.4.28
Requires-Dist: equinox==0.11.4
Requires-Dist: diffrax==0.5.1
Requires-Dist: optax==0.2.3
Requires-Dist: dm-haiku==0.0.12
Requires-Dist: pymoo==0.6.1.1
Requires-Dist: exciting-environments==0.2.4
Dynamic: license-file
